jw_download/__init__.py
jw_download/config.py
jw_download/config_default.yaml
jw_download/main.py
jw_download/task.py
jw_download-0.1.0.dist-info/entry_points.txt
jw_download-0.1.0.dist-info/WHEEL
jw_download-0.1.0.dist-info/METADATA
jw_download-0.1.0.dist-info/RECORD
