Metadata-Version: 2.1
Name: jw-download
Version: 0.1.0
Summary: 
License: MIT
Author: Unviray
Author-email: unviray@gmail.com
Requires-Python: >=3.8,<4.0
Classifier: License :: OSI Approved :: MIT License
Classifier: Programming Language :: Python :: 3
Classifier: Programming Language :: Python :: 3.8
Requires-Dist: click (>=7.1.2,<8.0.0)
Requires-Dist: confuse (>=1.3.0,<2.0.0)
Requires-Dist: requests (>=2.24.0,<3.0.0)
Requires-Dist: tqdm (>=4.51.0,<5.0.0)
Requires-Dist: yaspin (>=1.2.0,<2.0.0)
